{"userPokémon":[["61550544844061",{"name":"Jigglypuff","level":32,"value":1574820000,"nickname":"Cottoncandy","wins":101}],["100095187231024",{"name":"Munchlax","level":30,"value":1516140000,"wins":1,"nickname":"Laging naka higa"}],["100047718381724",{"name":"Pikachu","level":14,"value":1679400000}],["100087884534468",{"name":"Wynaut","level":23,"value":1878450000,"losses":2}],["100080818961203",{"name":"Pikachu","level":22,"value":1529100000,"wins":1}],["100070457100745",{"name":"Piplup","level":1,"value":1873500000,"losses":1}],["100094188970406",{"name":"Chikorita","level":14,"value":1576920000,"wins":1}],["100048921526608",{"name":"Seel","level":8,"value":1794510000}],["61550577081417",{"name":"Caterpie","level":5,"losses":99,"value":1864620000}],["100094060640003",{"name":"Scyther","level":12,"value":1667610000}],["100070522654041",{"name":"Chikorita","level":19,"value":1828470000}],["61550062792212",{"name":"Froakie","level":3,"value":1612740000}],["100094735906727",{"name":"Meowth","level":2,"value":1738230000,"losses":1}],["100093638410327",{"name":"Pikachu","level":11,"value":1551900000,"losses":1}],["100090187977698",{"name":"Jigglypuff","level":3,"value":1688340000}],["100076894970511",{"name":"Charmander","level":2,"value":1688250000}],["61550762078029",{"name":"Munchlax","level":2,"value":1688250000}],["100085948260631",{"name":"Psyduck","level":8,"value":1577850000}],["100091060972647",{"name":"Magikarp","level":22,"value":1514670000}],["100038060173505",{"name":"Sylveon","level":6,"value":1644030000}],["100093405445459",{"name":"Chikorita","level":20,"value":1591650000,"wins":2}],["100091151131122",{"name":"Froakie","level":26,"value":1516140000}],["61550752604406",{"name":"Mew","level":5,"value":1590690000}],["61551367857749",{"name":"Pikachu","level":2,"value":1618110000}],["100056979852137",{"name":"Charmander","level":10,"value":1523250000,"losses":1}],["100064955375325",{"name":"Mew","level":1,"value":1616880000}],["100080028102173",{"name":"Chikorita","level":2,"value":1591170000}],["100075158082965",{"name":"Squirtle","level":18,"value":1518030000,"losses":1,"nickname":"Vi"}],["100069361144675",{"name":"Pikachu","level":1,"value":1590540000}],["100034319023090",{"name":"Pikachu","level":4,"value":1581240000}],["100050438019044",{"name":"Bulbasaur","level":4,"value":1518000000}],["100093170119796",{"name":"Scyther","level":11,"value":852900000,"losses":1,"wins":1}],["100088688693632",{"name":"Pikachu","level":2,"value":1078380000,"wins":1}],["100094278233783",{"name":"Charmander","level":15,"value":1022820000,"wins":1}],["61550090780565",{"name":"Eevee","level":8,"value":1066890000}],["61551298846531",{"name":"Eevee","level":5,"value":960240000}],["61550769210485",{"name":"Psyduck","level":1,"value":1064790000}],["100085294794507",{"name":"Squirtle","level":22,"value":953730000}],["100004050946923",{"name":"Mew","level":47,"value":783360000,"nickname":"Ming"}],["100087404719542",{"name":"Scyther","level":15,"value":896580000}],["61552287451715",{"name":"Scyther","level":2,"value":1058610000}],["100076620457032",{"name":"Pikachu","level":15,"value":788550000}],["100073968137504",{"name":"Vulpix","level":11,"value":1055820000}],["100094646226708",{"name":"Charmander","level":17,"value":960900000}],["100093964582023",{"name":"Pikachu","level":5,"nickname":"kai","value":1046070000,"wins":1}],["100062690423414",{"name":"Jigglypuff","level":2,"value":1045920000,"losses":1}],["100034706178779",{"name":"Scyther","level":27,"value":887040000,"wins":20,"losses":1}],["100084235390819",{"name":"Pikachu","level":7,"value":1043340000,"losses":1}],["100091549657930",{"name":"Elekid","level":2,"value":1019010000}],["100084226389791",{"name":"Pikachu","level":1,"value":1041450000}],["100059467267656",{"name":"Pikachu","level":30,"value":904710000,"wins":1}],["61551877772698",{"name":"Pikachu","level":13,"value":951180000}],["100064085506937",{"name":"Charmander","level":2,"value":967110000}],["100003207011395",{"name":"Mew","level":7,"value":797100000}],["100094304403053",{"name":"Vulpix","level":1,"value":797250000}],["61551526207025",{"name":"Pikachu","level":5,"value":1011270000}],["100092593625215",{"name":"Froakie","level":6,"value":870390000}],["100087223119367",{"name":"Pikachu","level":9,"value":963480000,"nickname":"🐉Dragon🐉","losses":3}],["100019008836434",{"name":"Pikachu","level":9,"value":878910000}],["100094151679758",{"name":"Pikachu","level":14,"value":926100000}],["61551131846040",{"name":"Mew","level":6,"value":953760000}],["100092668630167",{"name":"Entei","level":19,"value":879660000,"wins":1}],["100081997942394",{"name":"Charmander","level":5,"value":919140000}],["100089994400115",{"name":"Mew","level":4,"value":780720000}],["61550593696267",{"name":"Scyther","level":22,"value":816660000,"wins":19,"losses":3}],["100027223084147",{"name":"Vaporeon","level":4,"value":878820000,"losses":4,"nickname":"kung ako yan di kita gaganyanin"}],["61550076692017",{"name":"Pikachu","level":19,"value":837390000,"wins":16,"losses":2}],["100094451610440",{"name":"Pikachu","level":6,"value":875040000,"wins":4,"losses":1}],["61552400236019",{"name":"Meowth","level":4,"value":894420000,"wins":2,"losses":1}],["100094435747452",{"name":"Pikachu","level":4,"value":886020000,"wins":1,"losses":2}],["100023850135867",{"name":"Sylveon","level":2,"value":897270000}],["100084291371134",{"name":"Clefairy","level":2,"value":874350000,"losses":5,"wins":2}],["100079185196686",{"name":"Pikachu","level":2,"value":856080000}],["61550847655496",{"name":"Pikachu","level":14,"value":890670000,"losses":20,"wins":3}],["100073623947556",{"name":"Vulpix","level":5,"value":880380000,"losses":6}],["61551361075435",{"name":"Pikachu","level":1,"value":880860000}],["100093101146755",{"name":"Arceus","level":12,"value":858420000,"losses":1,"wins":10,"nickname":"Sanvid"}],["100092286064912",{"name":"Bulbasaur","level":13,"value":875970000,"losses":2}],["61550812804665",{"name":"Pikachu","level":3,"losses":4,"value":877500000}],["100087899105880",{"name":"Cyndaquil","level":8,"value":877140000,"losses":2}],["100094168231495",{"name":"Arceus","level":20,"losses":2,"value":876090000,"nickname":"Mark"}],["100092499570016",{"name":"Mew","level":2,"value":874470000,"wins":1}],["100090360282235",{"name":"Entei","level":1,"value":874290000}],["100094965458947",{"name":"Pikachu","level":2,"value":873480000}],["61552222971223",{"name":"Arceus","level":4,"nickname":"kaz","value":783870000}],["100080266959147",{"name":"Abra","level":1,"value":856320000}],["61552270284469",{"name":"Squirtle","level":3,"value":851370000}],["100094086862257",{"name":"Arceus","level":6,"value":793110000}],["100094353195703",{"name":"Pikachu","level":1,"value":836400000}],["100039157099292",{"name":"Magikarp","level":4,"value":814590000}],["61550012862870",{"name":"Pikachu","level":5,"value":814560000,"losses":1}],["61550528626822",{"name":"Pikachu","level":3,"value":834210000}],["100091522458512",{"name":"Arceus","level":3,"value":793350000}],["100093456247452",{"name":"Pikachu","level":6,"value":220800000}],["100035902632557",{"name":"Mew","level":4,"value":672060000}],["100064451300101",{"name":"Bulbasaur","level":5,"value":610050000}],["100071943944060",{"name":"Abra","level":5,"value":669810000}],["100073334764307",{"name":"Pikachu","level":9,"value":631170000}],["61551301793648",{"name":"Mew","level":10,"value":372240000}],["100038167551355",{"name":"Mew","level":5,"value":579120000}],["100089453437795",{"name":"Pikachu","level":7,"nickname":"titi","value":462900000,"losses":1}],["61553748113208",{"name":"Mew","level":7,"value":579120000,"wins":1}],["100034065047763",{"name":"Pikachu","level":5,"value":592380000}],["100072766067269",{"name":"Marill","level":22,"value":273240000,"wins":1}],["100085066085508",{"name":"Squirtle","level":30,"value":461850000}],["100071104595354",{"name":"Pikachu","level":2,"value":566430000}],["61551583220407",{"name":"Pikachu","level":4,"losses":1,"value":441690000}],["100080613227213",{"name":"Pikachu","level":1,"nickname":"zakemyloves","value":547050000}],["100086549915582",{"name":"Mew","level":2,"value":507900000}],["100094000322061",{"name":"Pikachu","level":1,"value":230100000}],["100058709002039",{"name":"Pikachu","level":16,"value":10620000,"wins":10}],["61552824815444",{"name":"Pikachu","level":1,"value":197640000}],["100091965318259",{"name":"Mew","level":6,"value":28200000,"losses":9}],["100085357472559",{"name":"Mew","level":1,"value":93750000,"losses":1}]],"lastFeedTimestamps":[["61550544844061",1696419129226],["100095187231024",1696502970515],["100087884534468",1695015204026],["100047718381724",1695015429838],["100080818961203",1696502982695],["100094188970406",1696308175813],["61550577081417",1694661039096],["100048921526608",1694789200961],["100094060640003",1696080581708],["100070522654041",1696162162432],["100091060972647",1696563950056],["61550062792212",1696162586273],["100094735906727",1695009574916],["100093638410327",1696400788644],["100090187977698",1700314626337],["61550762078029",1695444024728],["100076894970511",1695444032712],["100085948260631",1696304450597],["100038060173505",1696077599591],["100093405445459",1696563337906],["100091151131122",1696550745907],["100034319023090",1696444835644],["61550752604406",1696251883697],["61551367857749",1696140440995],["100056979852137",1696563353790],["100080028102173",1696173060757],["100075158082965",1696549519859],["100050438019044",1696562477416],["100092668630167",1699482092941],["100093170119796",1699283064856],["100088688693632",1698326349294],["100094278233783",1699146251291],["61550090780565",1699205053078],["61551298846531",1698809119879],["100004050946923",1699565896054],["100085294794507",1698837444009],["100087404719542",1699349428697],["61552287451715",1698408942365],["100076620457032",1699543349378],["100073968137504",1699469339400],["100094646226708",1698804799597],["100019008836434",1699173732711],["100062690423414",1698540613558],["100093964582023",1698629198376],["100034706178779",1699504223070],["100084235390819",1698743421087],["100059467267656",1699518700870],["100091522458512",1699551610865],["61551877772698",1698849008562],["100092499570016",1699191654753],["61551361075435",1698538556792],["100091549657930",1698569222796],["100003207011395",1699509819698],["61551526207025",1698668049044],["100092593625215",1699208141584],["100087223119367",1699280257210],["100094151679758",1699261171800],["61551131846040",1698837545780],["100064085506937",1698780510635],["100081997942394",1699156753826],["100089994400115",1699544135709],["100094168231495",1699568102883],["61550593696267",1699567500359],["100027223084147",1699172349557],["61550076692017",1699569719199],["61552400236019",1699152542115],["100094451610440",1699167291040],["100094435747452",1699192032127],["100023850135867",1699099000458],["100084291371134",1699102141903],["100087899105880",1699567627114],["100092286064912",1699567527787],["100079185196686",1699116701338],["61550847655496",1699416900578],["100094086862257",1699530576194],["100073623947556",1699359401367],["100093101146755",1699534231430],["61550812804665",1699354629429],["100090360282235",1699191701617],["100094965458947",1699195796376],["61552222971223",1699563712801],["100039157099292",1699575663386],["61552270284469",1699349452140],["61550012862870",1699540724418],["61550528626822",1699437789452],["100093456247452",1702081855240],["100064451300101",1700390962451],["100071943944060",1700960621564],["100035902632557",1700914352160],["100073334764307",1700950980828],["100038167551355",1700999462222],["100089453437795",1701040414103],["61551301793648",1701417764130],["61553748113208",1700785009069],["100034065047763",1701208370261],["100072766067269",1701866791891],["100091965318259",1702872218960],["100085066085508",1702506172278],["100071104595354",1700571075225],["61551583220407",1701078097204],["100086549915582",1700810532187],["100058709002039",1702942726262]]}